{
  "index_settings": {
    "docstore_compression": "lz4",
    "docstore_blocksize": 16384
  },
  "segments": [
    {
      "segment_id": "08c2aca3-9472-459b-aafc-7577055d2b35",
      "max_doc": 619,
      "deletes": null
    },
    {
      "segment_id": "8bfbee6d-1402-43aa-849c-90b2747cab0f",
      "max_doc": 371,
      "deletes": null
    },
    {
      "segment_id": "3489b52c-1ccf-44e2-a8b8-a7a63eb33f14",
      "max_doc": 336,
      "deletes": null
    }
  ],
  "schema": [
    {
      "name": "id",
      "type": "text",
      "options": {
        "indexing": {
          "record": "basic",
          "fieldnorms": true,
          "tokenizer": "raw"
        },
        "stored": true,
        "fast": false
      }
    },
    {
      "name": "content",
      "type": "text",
      "options": {
        "indexing": {
          "record": "position",
          "fieldnorms": true,
          "tokenizer": "frankensearch_default"
        },
        "stored": true,
        "fast": false
      }
    },
    {
      "name": "title",
      "type": "text",
      "options": {
        "indexing": {
          "record": "position",
          "fieldnorms": true,
          "tokenizer": "frankensearch_default"
        },
        "stored": true,
        "fast": false
      }
    },
    {
      "name": "metadata_json",
      "type": "text",
      "options": {
        "stored": true,
        "fast": false
      }
    }
  ],
  "opstamp": 31745
}
